github_vanity/__init__.py
github_vanity/console.py
github_vanity/font.py
github_vanity/write.py
github_vanity-0.1.1.dist-info/DESCRIPTION.rst
github_vanity-0.1.1.dist-info/METADATA
github_vanity-0.1.1.dist-info/RECORD
github_vanity-0.1.1.dist-info/WHEEL
github_vanity-0.1.1.dist-info/entry_points.txt
github_vanity-0.1.1.dist-info/metadata.json
github_vanity-0.1.1.dist-info/top_level.txt
