Metadata-Version: 2.0
Name: github-vanity
Version: 0.1.1
Summary: Write to your GitHub activity chart
Home-page: https://github.com/ihabunek/github-vanity/
Author: Ivan Habunek
Author-email: ivan.habunek@gmail.com
License: MIT
Keywords: github vanity activity chart write
Platform: UNKNOWN
Classifier: Development Status :: 4 - Beta
Classifier: Intended Audience :: Developers
Classifier: License :: OSI Approved :: MIT License
Classifier: Programming Language :: Python :: 2
Classifier: Programming Language :: Python :: 2.6
Classifier: Programming Language :: Python :: 2.7
Classifier: Programming Language :: Python :: 3
Classifier: Programming Language :: Python :: 3.2
Classifier: Programming Language :: Python :: 3.3
Classifier: Programming Language :: Python :: 3.4
Classifier: Programming Language :: Python :: 3.5
Classifier: Programming Language :: Python :: 3.6
Requires-Dist: GitPython (>=2.1.0)
